<play>
  <stage>
    <model>WMDSoulpepper</model>
  </stage>
  <cast>
    <character id="Shawn">
      <name>Shawn</name>
      <color>0.005340739 0.0122074 0.5453352</color>
      <model>PersonBigPrefab</model>
    </character>
    <character id="USLGirder">
      <name>USLGirder</name>
      <color>1 0.88 0.79</color>
      <model>SoundEmitterPrefab</model>
    </character>
    <character id="SRGirder">
      <name>SRGirder</name>
      <color>1 0.88 0.79</color>
      <model>SoundEmitterPrefab</model>
    </character>
    <character id="Cape">
      <name>Cape</name>
      <color>0.1 0.1 0.1</color>
      <model>PersonBigPrefab</model>
    </character>
    <character id="Sidewalk">
      <name>Sidewalk</name>
      <color>1 0.88 0.79</color>
      <model>SoundEmitterPrefab</model>
    </character>
    <character id="Glidden">
      <name>Glidden</name>
      <color>0.71 0.16 0.51</color>
      <model>PersonBigPrefab</model>
    </character>
    <character id="Sasha">
      <name>Sasha</name>
      <color>0.1 0.3 0.3</color>
      <model>PersonBigPrefab</model>
    </character>
  </cast>
  <acts>
    <act id="act1">
      <name>Act 1</name>
      <scenes>
        <scene id="scene1">
          <name>Chapter 1</name>
          <destinations>
            <destination character="Glidden" endTime="0">-0.753912 0.0003996737 -7.812908</destination>
            <destination character="Glidden" endTime="72">-0.753912 0.0003996737 -7.812908</destination>
            <destination character="Glidden" endTime="74.5">0.8002515 1.0164 -7.209766</destination>
            <destination character="Glidden" endTime="77">3.474581 1.0164 -7.044732</destination>
            <destination character="Glidden" endTime="100">3.474581 1.0164 -7.044732</destination>
            <destination character="USLGirder" endTime="0">7.340566 4.394602 -4.462334</destination>
            <destination character="SRGirder" endTime="0">8.610859 4.394602 -3.179357</destination>
            <destination character="Cape" endTime="0">11.11943 0.0004066618 11.72723</destination>
            <destination character="Cape" endTime="5">11.0562 0.0004039392 4.114269</destination>
            <destination character="Cape" endTime="10">5.043626 0.0004039178 4.054391</destination>
            <destination character="Cape" endTime="12">5.069237 -0.08783571 3.102798</destination>
            <destination character="Cape" endTime="18">5.056259 0.1983621 -1.599582</destination>
            <destination character="Cape" endTime="25">1.186467 0.198362 -1.781952</destination>
            <destination character="Cape" endTime="26">1.062711 0.198362 -2.075915</destination>
            <destination character="Cape" endTime="26.25">1.077332 0.1528017 -2.321595</destination>
            <destination character="Cape" endTime="26.5">1.119318 0.0004015652 -2.52409</destination>
            <destination character="Cape" endTime="32">4.418743 0 -3.521475</destination>
            <destination character="Cape" endTime="33">4.471672 0 -3.241045</destination>
            <destination character="Cape" endTime="74">4.471672 0 -3.241045</destination>
            <destination character="Cape" endTime="77">4.668502 0 -4.62345</destination>
            <destination character="Cape" endTime="84">6.916938 0 -4.762898</destination>
            <destination character="Cape" endTime="86">6.678586 0 -4.966446</destination>
            <destination character="Sidewalk" endTime="0">0.2941017 -0.9266981 -1.209647</destination>
            <destination character="Shawn" endTime="0">8.898291 -0.9272037 -1.688603</destination>
            <destination character="Shawn" endTime="0.01">8.898291 -0.9272037 -1.788603</destination>
            <destination character="Sasha" endTime="0">4.779696 0.3687043 4.959614</destination>
            <destination character="Sasha" endTime="0.01">4.779696 0.3687043 4.859614</destination>
          </destinations>
          <actions />
          <lines>
            <line character="Cape" startTime="33" pace="0.8203957">Did it even happen? Sure it happened. It happened, I’m not crazy, I know! I arrived at the Bloor Street bridge, and I climbed up on the wall, right? And I was gonna do it, I was just about to jump when I heard this drum sound, as if the whole city knew, boom boom boom boom BOOM BOOM BOOM BOOM BOOM BOOM (speaks in small strange voice) “I’m not gonna hurt you.”</line>
            <line character="Cape" startTime="51" pace="1">Who’s that? A cop? There’s nobody! Just! A white dog! Beside me! How did it…</line>
            <line character="Cape" startTime="56" pace="1">“YOU’RE JUMPING TO HELL” the dog, the dog spoke.</line>
            <line character="Cape" startTime="59" pace="2">So I…answered-</line>
            <line character="Cape" startTime="60.5" pace="1">“BUT I’M LIVING IN HELL…ANYWAY.”</line>
            <line character="Cape" startTime="62.5" pace="0.75">“YOU’RE LIVING IN HELL, ‘CAUSE YOU AIN’T DONE YOUR MISSION.”</line>
            <line character="Cape" startTime="65" pace="2">“WHAT’S THAT?”</line>
            <line character="Cape" startTime="66.5" pace="0.65">“TO SAVE YOUR FATHER FROM DEATH, TO SAVE YOUR FATHER FROM DEATH.”</line>
            <line character="Cape" startTime="69.36667" pace="0.6491228">The dog…spoke! I’m not kidding! This dog actually spoke she saved me from the plunge; it was the weirdest-</line>
            <line character="Glidden" startTime="73.36667" pace="5.533333">OUT OF THE TUNNEL, […]</line>
          </lines>
          <beats>0</beats>
        </scene>
      </scenes>
    </act>
  </acts>
  <annotations>
    <annotation startTime="10" sd="false" endTime="20" character="Sidewalk" image="file://fig3b.jpg">"The sidewalk comes to function as a metonymy of the external forces that penetrate and destroy...the sidewalk is located in the midst of the audience and literally connects the fictional world of the play with the real world outside the auditorium" (Nunn 27, 28)</annotation>
    <annotation startTime="50" sd="false" endTime="51" character="Cape">(Turns quickly.)</annotation>
    <annotation startTime="52" sd="false" endTime="62" character="SRGirder" image="file://fig4.jpg">Stage Right Girder                                          .</annotation>
    <annotation startTime="62" sd="false" endTime="72" character="USLGirder" image="file://fig4.jpg">Upstage Left Girder                                          .</annotation>
    <annotation startTime="73.5" sd="false" endTime="74.5" character="Glidden">(GLIDDEN rushes out of bed, and out of his room onto the landing.)</annotation>
    <annotation startTime="80" sd="false" endTime="85">LePage, Sue, designer. Technical Drawings for White Biting Dog. Tarragon Theatre, Toronto, 1984. L.W. Conolly Theatre Archives, Guelph, Ontario.</annotation>
    <annotation startTime="85" sd="false" endTime="90">Marshall, Raymond, stage manager. White Biting Dog. By Judith Thompson. Promptscript. L.W. Conolly Theatre Archives. Guelph, Ontario.</annotation>
    <annotation startTime="90" sd="false" endTime="95">Nunn, Robert. "Spatial Metaphors in the Plays of Judith Thompson." Judith Thompson.  Critical Perspectives in Canadian Theatre. Vol. 3. Toronto: Playwrights Canada Press, 2005. 20-40. Print.</annotation>
    <annotation startTime="95" sd="false" endTime="100">Read, Kelly, associate technical director. Technical Drawings for White Biting Dog. Soulpepper Theatre, Toronto, 2011.</annotation>
  </annotations>
  <views>
    <view id="0">
      <location>-4.385894 3.342669 -1.299346</location>
      <lookAt>-1.910699 -0.3874767 0.9276303</lookAt>
      <name>Risers L</name>
    </view>
    <view id="1">
      <location>-1.891978 3.203951 -6.497033</location>
      <lookAt>0.1781867 -0.2721663 -3.559172</lookAt>
      <name>HL</name>
    </view>
    <view id="2">
      <location>3.351589 2.359602 -0.9326224</location>
      <lookAt>-0.228111 -0.424998 1.17255</lookAt>
      <name>Risers</name>
    </view>
    <view id="3">
      <location>5.116447 1.706296 -5.578904</location>
      <lookAt>2.196338 -1.078587 -2.626381</lookAt>
      <name>HR Stage</name>
    </view>
    <view id="4">
      <location>7.861344 4.324086 -8.35428</location>
      <lookAt>5.16193 1.120389 -5.624904</lookAt>
      <name>HR Zout</name>
    </view>
    <view id="5">
      <location>8.653896 4.658271 -1.02129</location>
      <lookAt>5.997387 0.4251146 -0.868488</lookAt>
      <name>FHR</name>
    </view>
    <view id="HL ZOut">
      <location>-2.566607 4.295998 -7.45443</location>
      <lookAt>-0.8351558 0.3004479 -4.997265</lookAt>
      <name>HL ZOut</name>
    </view>
  </views>
</play>